friendly_sonar/lint.py
friendly_sonar-0.0.1.dev4.dist-info/DESCRIPTION.rst
friendly_sonar-0.0.1.dev4.dist-info/METADATA
friendly_sonar-0.0.1.dev4.dist-info/RECORD
friendly_sonar-0.0.1.dev4.dist-info/WHEEL
friendly_sonar-0.0.1.dev4.dist-info/metadata.json
friendly_sonar-0.0.1.dev4.dist-info/pbr.json
friendly_sonar-0.0.1.dev4.dist-info/top_level.txt
