Metadata-Version: 2.0
Name: friendly-sonar
Version: 0.0.1.dev4
Summary: Python3 library to statically analyze software using SonarLint and collect data in a Python Object, CSV, or JSON data format
Home-page: https://luiscruz.github.io/
Author: Luis Cruz
Author-email: luismirandacruz@gmail.com
License: MIT
Platform: UNKNOWN
Classifier: Development Status :: 4 - Beta
Classifier: Environment :: Plugins
Classifier: Intended Audience :: Science/Research
Classifier: Intended Audience :: Developers
Classifier: Intended Audience :: Information Technology
Classifier: Operating System :: OS Independent
Classifier: Programming Language :: Python
Classifier: License :: OSI Approved :: MIT License
Classifier: Topic :: Software Development :: Libraries
Classifier: Topic :: Scientific/Engineering
Classifier: Topic :: Utilities
Requires-Dist: click
